kbm/__init__.py
kbm/config/__init__.py
kbm/filer/__init__.py
klipper_backup_manager/__about__.py
klipper_backup_manager/__init__.py
klipper_backup_manager/klipper_backup_manager.py
klipper_backup_manager-3.0.9.dist-info/METADATA
klipper_backup_manager-3.0.9.dist-info/WHEEL
klipper_backup_manager-3.0.9.dist-info/entry_points.txt
klipper_backup_manager-3.0.9.dist-info/licenses/LICENSE.txt
klipper_backup_manager-3.0.9.dist-info/RECORD
