Metadata-Version: 2.1
Name: klipper-backup-manager
Version: 3.0.9
Summary: A set of tools for managing, creating, and restoring backups of configurations, customizations, and gcodes for Klipper-based 3D printing setups.
Project-URL: Documentation, https://github.com/venus-de-lmao/klipper-backup-manager#readme
Project-URL: Issues, https://github.com/venus-de-lmao/klipper-backup-manager/issues
Project-URL: Source, https://github.com/venus-de-lmao/klipper-backup-manager
Author-email: Laurel Ash <laurel.ash@proton.me>
License-Expression: GPL-3.0-or-later
License-File: LICENSE.txt
Keywords: 3d printing,backup,klipper
Classifier: Development Status :: 4 - Beta
Classifier: Programming Language :: Python
Classifier: Programming Language :: Python :: 3.8
Classifier: Programming Language :: Python :: 3.9
Classifier: Programming Language :: Python :: 3.10
Classifier: Programming Language :: Python :: 3.11
Classifier: Programming Language :: Python :: 3.12
Classifier: Programming Language :: Python :: Implementation :: CPython
Classifier: Programming Language :: Python :: Implementation :: PyPy
Requires-Python: >=3.8
Requires-Dist: click
Requires-Dist: cloup
Requires-Dist: pyyaml
Requires-Dist: tqdm
